ceevee/__init__.py
ceevee/__version__.py
ceevee/base.py
ceevee/cli.py
ceevee/cv_http.py
ceevee/utils.py
ceevee/dummy/__init__.py
ceevee-0.0.1.dist-info/METADATA
ceevee-0.0.1.dist-info/WHEEL
ceevee-0.0.1.dist-info/top_level.txt
ceevee-0.0.1.dist-info/RECORD
