Metadata-Version: 2.1
Name: ceevee
Version: 0.0.1
Summary: Python library for various computer vision problems with a focus on easy usage
Home-page: https://github.com/arsenyinfo/ceevee
Author: [ods.ai] Arseny Kravchenko et al
License: UNKNOWN
Keywords: Machine Learning,Deep Learning,Computer Vision,PyTorch
Platform: UNKNOWN
Classifier: Programming Language :: Python
Classifier: Programming Language :: Python :: 3.6
Classifier: Programming Language :: Python :: 3.7
Requires-Python: >=3.6.0
Requires-Dist: numpy (>=1.16.4)
Requires-Dist: torch (>=1.0)
Requires-Dist: torchvision (>=0.3)
Requires-Dist: falcon
Requires-Dist: falcon-multipart
Requires-Dist: fire
Requires-Dist: opencv-python-headless
Requires-Dist: PyYAML
Requires-Dist: tqdm
Requires-Dist: ujson
